bashurevershell/__init__.py
bashurevershell/__main__.py
bashurevershell/shell.py
bashurevershell-0.1.3.dist-info/licenses/LICENSE
bashurevershell-0.1.3.dist-info/METADATA
bashurevershell-0.1.3.dist-info/WHEEL
bashurevershell-0.1.3.dist-info/top_level.txt
bashurevershell-0.1.3.dist-info/RECORD
