Metadata-Version: 2.4
Name: bashurevershell
Version: 0.1.3
Summary: A reverse shell package by Bashu
License-File: LICENSE
Dynamic: license-file
